setup.py
scripts/upstart-create
scripts/upstart-reload
upstart/__init__.py
upstart/_version.py
upstart/job.py
upstart/job_builder.py
upstart/system.py
upstart_new.egg-info/PKG-INFO
upstart_new.egg-info/SOURCES.txt
upstart_new.egg-info/dependency_links.txt
upstart_new.egg-info/not-zip-safe
upstart_new.egg-info/top_level.txt